word_injection/__init__.py
word_injection/callback.py
word_injection/model.py
word_injection-0.1.3.dist-info/LICENSE
word_injection-0.1.3.dist-info/METADATA
word_injection-0.1.3.dist-info/WHEEL
word_injection-0.1.3.dist-info/RECORD
