Metadata-Version: 2.1
Name: word-injection
Version: 0.1.3
Summary: Fine-tuning Sentence Transformers with Word Injection technique
License: Apache-2.0
Author: Kacper Łukawski
Author-email: lukawski.kacper@gmail.com
Requires-Python: >=3.10,<4.0
Classifier: License :: OSI Approved :: Apache Software License
Classifier: Programming Language :: Python :: 3
Classifier: Programming Language :: Python :: 3.10
Classifier: Programming Language :: Python :: 3.11
Classifier: Programming Language :: Python :: 3.12
Requires-Dist: datasets (>=2.21.0,<3.0.0)
Requires-Dist: sentence-transformers (>=3.0.1,<4.0.0)
Requires-Dist: torch (>=2.2.2,<3.0.0)
Requires-Dist: transformers[torch] (>=4.41.2,<5.0.0)
